chssh
