Metadata-Version: 1.1
Name: chssh
Version: 0.4.1
Summary: ssh wrappers to transparently use chef node names instead of hostnames
Home-page: http://github.com/kriswehner/chssh
Author: Kris Wehner
Author-email: kris@further.com
License: BSD
Platform: UNKNOWN
Classifier: Development Status :: 5 - Production/Stable
Classifier: License :: OSI Approved :: BSD License
Classifier: Natural Language :: English
Classifier: Operating System :: OS Independent
Classifier: Programming Language :: Python
